nanollm/.coverage
nanollm/__init__.py
nanollm/cli.py
nanollm/models.py
nanollm/plugin_manager.py
nanollm/plugin_spec.py
nanollm/plugin_utils.py
nanollm/plugins/llama_cpp_plugin.py
nanollm/plugins/mlc_plugin.py
nanollm/plugins/mock_plugin.py
nanollm/plugins/openai_plugin.py
nanollm/sqlite_logging.py
nanollm/supress_output.py
nanollm/templates.py
nanollm-0.1.dist-info/METADATA
nanollm-0.1.dist-info/WHEEL
nanollm-0.1.dist-info/entry_points.txt
nanollm-0.1.dist-info/RECORD
