Metadata-Version: 2.1
Name: nanoLLM
Version: 0.1
Summary: nanoLLM is a flexible and efficent framework to create LLMs
License: Apache License
Author: James Liu
Author-email: james@bayjarvis.com
Requires-Python: >=3.10,<3.13
Classifier: License :: Other/Proprietary License
Classifier: Programming Language :: Python :: 3
Classifier: Programming Language :: Python :: 3.10
Classifier: Programming Language :: Python :: 3.11
Provides-Extra: opensource
Provides-Extra: test
Requires-Dist: python-dotenv (>=1.0.0,<2.0.0)
